setup.py
examples/__init__.py
examples/maze/__init__.py
examples/maze/callback.py
examples/maze/helper.py
examples/maze/task.py
examples/ticktacktoe/__init__.py
examples/ticktacktoe/callback.py
examples/ticktacktoe/helper.py
examples/ticktacktoe/task.py
kyoka/__init__.py
kyoka/callback.py
kyoka/policy.py
kyoka/task.py
kyoka/utils.py
kyoka/value_function.py
kyoka.egg-info/PKG-INFO
kyoka.egg-info/SOURCES.txt
kyoka.egg-info/dependency_links.txt
kyoka.egg-info/top_level.txt
kyoka/algorithm/__init__.py
kyoka/algorithm/deep_q_learning.py
kyoka/algorithm/montecarlo.py
kyoka/algorithm/montecarlo_tree_search.py
kyoka/algorithm/q_learning.py
kyoka/algorithm/rl_algorithm.py
kyoka/algorithm/sarsa.py
tests/__init__.py
tests/base_unittest.py
tests/utils.py
tests/examples/__init__.py
tests/examples/maze/__init__.py
tests/examples/maze/helper_test.py
tests/examples/maze/task_test.py
tests/examples/ticktacktoe/__init__.py
tests/examples/ticktacktoe/helper_test.py
tests/examples/ticktacktoe/task_test.py
tests/kyoka/__init__.py
tests/kyoka/callback_test.py
tests/kyoka/policy_test.py
tests/kyoka/task_test.py
tests/kyoka/utils_test.py
tests/kyoka/value_function_test.py
tests/kyoka/algorithm/__init__.py
tests/kyoka/algorithm/deep_q_learning_test.py
tests/kyoka/algorithm/montecarlo_test.py
tests/kyoka/algorithm/montecarlo_tree_search_test.py
tests/kyoka/algorithm/q_learning_test.py
tests/kyoka/algorithm/rl_algorithm_test.py
tests/kyoka/algorithm/sarsa_test.py