Metadata-Version: 1.1
Name: kyoka
Version: 0.2.0
Summary: Simple Reinforcement Learning Library
Home-page: https://github.com/ishikota/kyoka
Author: ishikota
Author-email: ishikota086@gmail.com
License: MIT
Keywords: reinforcement learning RL
Platform: UNKNOWN
Classifier: Development Status :: 4 - Beta
Classifier: Topic :: Scientific/Engineering :: Artificial Intelligence
Classifier: License :: OSI Approved :: MIT License
